LICENSE
MANIFEST.in
README.md
setup.py
aare/__init__.py
aare/aare.py
aare/tests/__init__.py
aare/tests/test_aare.py
aare/tests/utils.py
ftw.aare.egg-info/PKG-INFO
ftw.aare.egg-info/SOURCES.txt
ftw.aare.egg-info/dependency_links.txt
ftw.aare.egg-info/entry_points.txt
ftw.aare.egg-info/requires.txt
ftw.aare.egg-info/top_level.txt