Metadata-Version: 1.1
Name: ftw.aare
Version: 1.2
Summary: A Shell Command which displays the current temperature of the Aare in Bern, Switzerland
Home-page: https://github.com/4teamwork/ftw.aare
Author: Steven Pilatschek
Author-email: info@4teamwork.ch
License: MIT
Platform: UNKNOWN
Classifier: License :: OSI Approved :: MIT License
Classifier: Programming Language :: Python
Classifier: Programming Language :: Python :: 3
Classifier: Programming Language :: Python :: 3.5
Classifier: Programming Language :: Python :: 3.6
Classifier: Programming Language :: Python :: Implementation :: CPython
Classifier: Programming Language :: Python :: Implementation :: PyPy
